.gitignore
Dockerfile
LICENSE
Makefile
README.md
lol.py
main.py
requirements.txt
setup.py
spotify.csv
test_main.py
.devcontainer/Dockerfile
.devcontainer/devcontainer.json
.github/workflows/cicd.yml
my_csv_splitter.egg-info/PKG-INFO
my_csv_splitter.egg-info/SOURCES.txt
my_csv_splitter.egg-info/dependency_links.txt
my_csv_splitter.egg-info/entry_points.txt
my_csv_splitter.egg-info/requires.txt
my_csv_splitter.egg-info/top_level.txt