Metadata-Version: 1.0
Name: my-csv-splitter
Version: 1.0.0
Summary: A tool to split CSV files
Home-page: UNKNOWN
Author: Your Name
Author-email: UNKNOWN
License: UNKNOWN
Platform: UNKNOWN
